[
  {
    "name": "Eternal Cash",
    "address": "0x400df62C3052fDBaad8C74C0226147F9bFaaF7eC",
    "symbol": "EC",
    "decimals": 9,
    "chainId": 56,
    "logoURI": "https://bscscan.com/token/images/venus-vbtc_32.png"
  },
  {
    "name": "Extended Finance",
    "address": "0x6306e883493824ccf606d90e25f68a28e47b98a3",
    "symbol": "EXF",
    "decimals": 9,
    "chainId": 56,
    "logoURI": "https://bscscan.com/token/images/venus-vbtc_32.png"
  },
  {
    "name": "Binance USD Peg",
    "address": "0xe9e7CEA3DedcA5984780Bafc599bD69ADd087D56",
    "symbol": "BUSD",
    "decimals": 18,
    "chainId": 56,
    "logoURI": "https://cdn.coinranking.com/6SJHRfClq/busd.svg?size=48x48"
  }
]
